{
  "date": "2026.03.31",
  "kospi_close": 5052.46,
  "kospi_chg": -4.26,
  "kosdaq_close": 1052.39,
  "kosdaq_chg": -4.94,
  "fx_rate": 1531.1,
  "foreign_net": 0,
  "inst_net": 0,
  "news_headlines": [
    "코스피 5100 밑으로 추락…시장의 관심은 알루미늄 관련주로 [매경 자이앤트]",
    "한국증권금융, 예술인재 지원사업 '희망 드림 넥스트' 발대식",
    "'전쟁추경'인데…농어촌 기본소득 사업에 706억 반영",
    "삼천당제약, 재료소멸에 29.9% 급락 마감…'황제주' 지위 반납(종합)",
    "[특징주] 대한조선, 1분기만 연간 수주 목표 달성에 5%대 급등 마감(종합)",
    "삼성전자, 미성년 주주비율 8.2%…보유주식 평가액 1조9천억원",
    "국민연금 스왑 ‘리볼빙’ 협의…한은 “연금 판단 우선해 수급 조절”",
    "이찬우 NH농협금융지주 회장, NH證 IMA 1호 상품 가입",
    "미래아이앤지, '스텔라PE 체제' 공식 출범…원만한 경영권 이전",
    "전쟁 한달만 국내증시 시총 1천조원 증발…'삼전닉스' 473조원↓(종합)"
  ]
}