{
  "updated_at": "2026-04-02 09:37:00",
  "date": "2026.04.02",
  "total_stocks": 100,
  "top10": [
    {
      "rank": 1,
      "prev_rank": null,
      "name": "하나금융지주",
      "code": "086790",
      "market": "KOSPI",
      "sector": "금융",
      "value_score": 74,
      "signal": "watch",
      "rank_change": 0,
      "rank_change_reason": "",
      "date": "2026.04.02"
    },
    {
      "rank": 2,
      "prev_rank": null,
      "name": "우리금융지주",
      "code": "316140",
      "market": "KOSPI",
      "sector": "금융",
      "value_score": 72,
      "signal": "watch",
      "rank_change": 0,
      "rank_change_reason": "",
      "date": "2026.04.02"
    },
    {
      "rank": 3,
      "prev_rank": null,
      "name": "성우하이텍",
      "code": "015750",
      "market": "KOSPI",
      "sector": "자동차",
      "value_score": 68,
      "signal": "watch",
      "rank_change": 0,
      "rank_change_reason": "",
      "date": "2026.04.02"
    },
    {
      "rank": 4,
      "prev_rank": null,
      "name": "신한지주",
      "code": "055550",
      "market": "KOSPI",
      "sector": "금융",
      "value_score": 68,
      "signal": "hold",
      "rank_change": 0,
      "rank_change_reason": "",
      "date": "2026.04.02"
    },
    {
      "rank": 5,
      "prev_rank": null,
      "name": "현대모비스",
      "code": "012330",
      "market": "KOSPI",
      "sector": "자동차",
      "value_score": 65,
      "signal": "hold",
      "rank_change": 0,
      "rank_change_reason": "",
      "date": "2026.04.02"
    },
    {
      "rank": 6,
      "prev_rank": null,
      "name": "KB금융",
      "code": "105560",
      "market": "KOSPI",
      "sector": "금융",
      "value_score": 62,
      "signal": "hold",
      "rank_change": 0,
      "rank_change_reason": "",
      "date": "2026.04.02"
    },
    {
      "rank": 7,
      "prev_rank": null,
      "name": "금호석유",
      "code": "011780",
      "market": "KOSPI",
      "sector": "화학",
      "value_score": 62,
      "signal": "watch",
      "rank_change": 0,
      "rank_change_reason": "",
      "date": "2026.04.02"
    },
    {
      "rank": 8,
      "prev_rank": null,
      "name": "KT",
      "code": "030200",
      "market": "KOSPI",
      "sector": "통신",
      "value_score": 62,
      "signal": "hold",
      "rank_change": 0,
      "rank_change_reason": "",
      "date": "2026.04.02"
    },
    {
      "rank": 9,
      "prev_rank": null,
      "name": "GS",
      "code": "078930",
      "market": "KOSPI",
      "sector": "에너지",
      "value_score": 62,
      "signal": "watch",
      "rank_change": 0,
      "rank_change_reason": "",
      "date": "2026.04.02"
    },
    {
      "rank": 10,
      "prev_rank": null,
      "name": "대한항공",
      "code": "003490",
      "market": "KOSPI",
      "sector": "항공/물류",
      "value_score": 62,
      "signal": "watch",
      "rank_change": 0,
      "rank_change_reason": "",
      "date": "2026.04.02"
    }
  ],
  "market_sentiment": "긍정",
  "fear_greed_score": 68,
  "market_summary": "WGBI 편입 외인 매수·방산·조선 강세로 코스피 5500 안착 시도",
  "raw_market": {
    "kospi_close": 5532.66,
    "kospi_chg": 0.98,
    "kosdaq_close": 1121.55,
    "kosdaq_chg": 0.48,
    "fx_rate": 1513.4,
    "foreign_net": 0,
    "inst_net": 0
  },
  "sector_momentum": {
    "IT/반도체": 45,
    "자동차": 65,
    "금융": 60,
    "바이오": 20,
    "2차전지": 40,
    "조선": 70,
    "방산": 75,
    "화학": 15
  }
}